{
  "@context": [
    "https://www.w3.org/2018/credentials/v1",
    "https://w3id.org/vaccination/v1"
  ],
  "type": [
    "VerifiableCredential",
    "VaccinationCertificate"
  ],
  "id": "urn:uuid:92a6e0b1-ac84-4fdb-9343-90a784b3a21c",
  "name": "Typhoid",
  "description": "Typhoid",
  "expirationDate": null,
  "credentialSubject": {
    "type": "VaccinationEvent",
    "batchNumber": "396",
    "administeringCentre": "NiH",
    "healthProfessional": "NiH",
    "countryOfVaccination": "U.S.A.",
    "recipient": {
      "type": "VaccineRecipient",
      "givenName": "JOHN",
      "familyName": "SMITH",
      "gender": "Male",
      "birthDate": "1958-07-17"
    },
    "vaccine": {
      "type": "Vaccine",
      "disease": "Typhoid",
      "atcCode": "XM8BU8 "
    }
  }
}